{
    "Arn": "arn:aws:cloudformation:us-east-1::type/resource/AWS-SNS-TopicPolicy",
    "Type": "RESOURCE",
    "TypeName": "AWS::SNS::TopicPolicy",
    "IsDefaultVersion": true,
    "Description": "Schema for AWS::SNS::TopicPolicy",
    "Schema": "{\n    \"typeName\": \"AWS::SNS::TopicPolicy\",\n    \"description\": \"Schema for AWS::SNS::TopicPolicy\",\n    \"sourceUrl\": \"https://github.com/aws-cloudformation/aws-cloudformation-resource-providers-sns.git\",\n    \"additionalProperties\": false,\n    \"properties\": {\n        \"Id\": {\n            \"description\": \"The provider-assigned unique ID for this managed resource.\",\n            \"type\": \"string\"\n        },\n        \"PolicyDocument\": {\n            \"description\": \"A policy document that contains permissions to add to the specified SNS topics.\",\n            \"type\": [\n                \"object\",\n                \"string\"\n            ]\n        },\n        \"Topics\": {\n            \"description\": \"The Amazon Resource Names (ARN) of the topics to which you want to add the policy. You can use the [Ref](https://docs.aws.amazon.com/AWSCloudFormation/latest/UserGuide/intrinsic-function-reference-ref.html)` function to specify an [AWS::SNS::Topic](https://docs.aws.amazon.com/AWSCloudFormation/latest/UserGuide/aws-properties-sns-topic.html) resource.\",\n            \"type\": \"array\",\n            \"uniqueItems\": false,\n            \"insertionOrder\": false,\n            \"items\": {\n                \"type\": \"string\"\n            }\n        }\n    },\n    \"tagging\": {\n        \"taggable\": false,\n        \"tagOnCreate\": false,\n        \"tagUpdatable\": false,\n        \"cloudFormationSystemTags\": false\n    },\n    \"required\": [\n        \"PolicyDocument\",\n        \"Topics\"\n    ],\n    \"primaryIdentifier\": [\n        \"/properties/Id\"\n    ],\n    \"readOnlyProperties\": [\n        \"/properties/Id\"\n    ],\n    \"handlers\": {\n        \"create\": {\n            \"permissions\": [\n                \"sns:SetTopicAttributes\"\n            ]\n        },\n        \"update\": {\n            \"permissions\": [\n                \"sns:SetTopicAttributes\"\n            ]\n        },\n        \"delete\": {\n            \"permissions\": [\n                \"sns:SetTopicAttributes\"\n            ]\n        }\n    }\n}\n",
    "ProvisioningType": "NON_PROVISIONABLE",
    "DeprecatedStatus": "LIVE",
    "Visibility": "PUBLIC",
    "SourceUrl": "https://github.com/aws-cloudformation/aws-cloudformation-resource-providers-sns.git",
    "TimeCreated": "2020-11-05T21:50:25.324000+00:00"
}
