{
    "Arn": "arn:aws:cloudformation:us-east-1::type/resource/AWS-AmazonMQ-ConfigurationAssociation",
    "Type": "RESOURCE",
    "TypeName": "AWS::AmazonMQ::ConfigurationAssociation",
    "IsDefaultVersion": true,
    "Schema": "{\n  \"typeName\" : \"AWS::AmazonMQ::ConfigurationAssociation\",\n  \"description\" : \"Resource Type definition for AWS::AmazonMQ::ConfigurationAssociation\",\n  \"additionalProperties\" : false,\n  \"properties\" : {\n    \"Id\" : {\n      \"type\" : \"string\"\n    },\n    \"Broker\" : {\n      \"type\" : \"string\"\n    },\n    \"Configuration\" : {\n      \"$ref\" : \"#/definitions/ConfigurationId\"\n    }\n  },\n  \"definitions\" : {\n    \"ConfigurationId\" : {\n      \"type\" : \"object\",\n      \"additionalProperties\" : false,\n      \"properties\" : {\n        \"Revision\" : {\n          \"type\" : \"integer\"\n        },\n        \"Id\" : {\n          \"type\" : \"string\"\n        }\n      },\n      \"required\" : [ \"Revision\", \"Id\" ]\n    }\n  },\n  \"required\" : [ \"Configuration\", \"Broker\" ],\n  \"createOnlyProperties\" : [ \"/properties/Broker\" ],\n  \"primaryIdentifier\" : [ \"/properties/Id\" ],\n  \"readOnlyProperties\" : [ \"/properties/Id\" ]\n}",
    "ProvisioningType": "NON_PROVISIONABLE",
    "DeprecatedStatus": "LIVE",
    "Visibility": "PUBLIC",
    "TimeCreated": "2019-11-15T17:23:52.910000+00:00"
}
