{
    "Arn": "arn:aws:cloudformation:us-east-1::type/resource/AWS-Route53RecoveryReadiness-ReadinessCheck",
    "Type": "RESOURCE",
    "TypeName": "AWS::Route53RecoveryReadiness::ReadinessCheck",
    "IsDefaultVersion": true,
    "Description": "Aws Route53 Recovery Readiness Check Schema and API specification.",
    "Schema": "{\n    \"typeName\": \"AWS::Route53RecoveryReadiness::ReadinessCheck\",\n    \"description\": \"Aws Route53 Recovery Readiness Check Schema and API specification.\",\n    \"sourceUrl\": \"https://github.com/aws-cloudformation/aws-cloudformation-resource-providers-route53-recovery-readiness.git\",\n    \"taggable\": true,\n    \"definitions\": {\n      \"Tag\": {\n        \"type\": \"object\",\n        \"additionalProperties\": false,\n        \"properties\": {\n          \"Key\": {\n            \"type\": \"string\"\n          },\n          \"Value\": {\n            \"type\": \"string\"\n          }\n        },\n        \"required\": [\n          \"Value\",\n          \"Key\"\n        ]\n      }\n    },\n    \"properties\": {\n      \"ResourceSetName\": {\n        \"description\": \"The name of the resource set to check.\",\n        \"type\": \"string\",\n        \"pattern\": \"[a-zA-Z0-9_]+\",\n        \"minLength\": 1,\n        \"maxLength\": 64\n      },\n      \"ReadinessCheckName\": {\n        \"description\": \"Name of the ReadinessCheck to create.\",\n        \"type\": \"string\",\n        \"pattern\": \"[a-zA-Z0-9_]+\",\n        \"minLength\": 1,\n        \"maxLength\": 64\n      },\n      \"ReadinessCheckArn\": {\n        \"description\": \"The Amazon Resource Name (ARN) of the readiness check.\",\n        \"type\": \"string\",\n        \"maxLength\": 256\n      },\n      \"Tags\":{\n        \"description\": \"A collection of tags associated with a resource.\",\n        \"type\": \"array\",\n        \"items\": {\n          \"$ref\": \"#/definitions/Tag\",\n          \"maxItems\": 20\n        },\n        \"insertionOrder\": false\n      }\n    },\n    \"additionalProperties\": false,\n    \"createOnlyProperties\": [\n      \"/properties/ReadinessCheckName\"\n    ],\n    \"readOnlyProperties\": [\n      \"/properties/ReadinessCheckArn\"\n    ],\n    \"primaryIdentifier\": [\n      \"/properties/ReadinessCheckName\"\n    ],\n    \"handlers\": {\n      \"create\": {\n        \"permissions\": [\n          \"route53-recovery-readiness:CreateReadinessCheck\",\n          \"route53-recovery-readiness:GetResourceSet\",\n          \"route53-recovery-readiness:GetReadinessCheck\",\n          \"route53-recovery-readiness:ListTagsForResources\",\n          \"route53-recovery-readiness:TagResource\"\n        ]\n      },\n      \"read\": {\n        \"permissions\": [\n          \"route53-recovery-readiness:GetReadinessCheck\",\n          \"route53-recovery-readiness:ListTagsForResources\"\n        ]\n      },\n      \"update\": {\n        \"permissions\": [\n          \"route53-recovery-readiness:UpdateReadinessCheck\",\n          \"route53-recovery-readiness:GetResourceSet\",\n          \"route53-recovery-readiness:GetReadinessCheck\",\n          \"route53-recovery-readiness:ListTagsForResources\",\n          \"route53-recovery-readiness:TagResource\",\n          \"route53-recovery-readiness:UntagResource\"\n        ]\n      },\n      \"delete\": {\n        \"permissions\": [\n          \"route53-recovery-readiness:DeleteReadinessCheck\",\n          \"route53-recovery-readiness:GetReadinessCheck\"\n        ]\n      },\n      \"list\": {\n        \"permissions\": [\n          \"route53-recovery-readiness:ListReadinessChecks\",\n          \"route53-recovery-readiness:GetReadinessChecks\"\n        ]\n      }\n    }\n  }",
    "ProvisioningType": "FULLY_MUTABLE",
    "DeprecatedStatus": "LIVE",
    "Visibility": "PUBLIC",
    "SourceUrl": "https://github.com/aws-cloudformation/aws-cloudformation-resource-providers-route53-recovery-readiness.git",
    "TimeCreated": "2021-07-15T17:41:42.433000+00:00"
}
