{
    "Arn": "arn:aws:cloudformation:us-east-1::type/resource/AWS-RoboMaker-SimulationApplication",
    "Type": "RESOURCE",
    "TypeName": "AWS::RoboMaker::SimulationApplication",
    "IsDefaultVersion": true,
    "Description": "This schema is for testing purpose only.",
    "Schema": "{\n  \"typeName\": \"AWS::RoboMaker::SimulationApplication\",\n  \"description\": \"This schema is for testing purpose only.\",\n  \"sourceUrl\": \"https://github.com/aws-cloudformation/aws-cloudformation-rpdk.git\",\n  \"definitions\": {\n    \"Arn\": {\n      \"type\": \"string\",\n      \"pattern\": \"arn:[\\\\w+=/,.@-]+:[\\\\w+=/,.@-]+:[\\\\w+=/,.@-]*:[0-9]*:[\\\\w+=,.@-]+(/[\\\\w+=,.@-]+)*\"\n    },\n    \"Tags\": {\n      \"description\": \"A key-value pair to associate with a resource.\",\n      \"type\": \"object\",\n      \"additionalProperties\": false,\n      \"patternProperties\": {\n        \"^[a-zA-Z0-9-]{1,128}$\": {\n          \"type\": \"string\",\n          \"description\": \"The value for the tag. You can specify a value that is 1 to 255 Unicode characters in length and cannot be prefixed with aws:. You can use any of the following characters: the set of Unicode letters, digits, whitespace, _, ., /, =, +, and -.\",\n          \"minLength\": 1,\n          \"maxLength\": 256\n        }\n      }\n    },\n    \"RenderingEngine\" : {\n      \"description\": \"Information about a rendering engine.\",\n      \"type\": \"object\",\n      \"properties\": {\n        \"Name\" : {\n          \"type\": \"string\",\n          \"description\": \"The name of the rendering engine.\",\n          \"enum\": [\"OGRE\"]\n        },\n        \"Version\" : {\n          \"type\": \"string\",\n          \"description\": \"The version of the rendering engine.\",\n          \"pattern\": \"1.x\"\n        }\n      },\n      \"required\": [\n        \"Name\",\n        \"Version\"\n      ],\n      \"additionalProperties\": false\n    },\n    \"RobotSoftwareSuite\": {\n      \"description\": \"Information about a robot software suite.\",\n      \"type\": \"object\",\n      \"properties\": {\n        \"Name\": {\n          \"type\": \"string\",\n          \"description\": \"The name of the robot software suite.\",\n          \"enum\": [ \"ROS\", \"ROS2\", \"General\"]\n        },\n        \"Version\": {\n          \"type\": \"string\",\n          \"description\": \"The version of the robot software suite.\",\n          \"enum\": [ \"Kinetic\", \"Melodic\", \"Dashing\", \"Foxy\"]\n        }\n      },\n      \"required\": [\n        \"Name\"\n      ],\n      \"additionalProperties\": false\n    },\n    \"SourceConfig\": {\n      \"type\": \"object\",\n      \"description\": \"Information about a source configuration.\",\n      \"properties\": {\n        \"S3Bucket\": {\n          \"type\": \"string\",\n          \"description\": \"The Amazon S3 bucket name.\",\n          \"pattern\": \"[a-z0-9][a-z0-9.\\\\-]*[a-z0-9]\"\n        },\n        \"S3Key\": {\n          \"type\": \"string\",\n          \"description\": \"The s3 object key.\",\n          \"minLength\": 1,\n          \"maxLength\": 1024\n        },\n        \"Architecture\": {\n          \"type\": \"string\",\n          \"description\": \"The target processor architecture for the application.\",\n          \"enum\": [ \"X86_64\", \"ARM64\", \"ARMHF\"]\n        }\n      },\n      \"required\": [\n        \"S3Bucket\",\n        \"S3Key\",\n        \"Architecture\"\n      ],\n      \"additionalProperties\": false\n    },\n    \"SimulationSoftwareSuite\": {\n      \"description\": \"Information about a simulation software suite.\",\n      \"type\": \"object\",\n      \"properties\": {\n        \"Name\": {\n          \"type\": \"string\",\n          \"description\": \"The name of the simulation software suite.\",\n          \"enum\": [ \"Gazebo\", \"RosbagPlay\", \"SimulationRuntime\"]\n        },\n        \"Version\": {\n          \"type\": \"string\",\n          \"description\": \"The version of the simulation software suite.\",\n          \"enum\": [ \"7\", \"9\", \"11\", \"Kinetic\", \"Melodic\", \"Dashing\", \"Foxy\"]\n        }\n      },\n      \"required\": [\n        \"Name\"\n      ],\n      \"additionalProperties\": false\n    }\n  },\n  \"properties\": {\n    \"Arn\": {\n      \"$ref\": \"#/definitions/Arn\"\n    },\n    \"Name\" : {\n      \"description\": \"The name of the simulation application.\",\n      \"type\": \"string\",\n      \"minLength\": 1,\n      \"maxLength\": 255,\n      \"pattern\": \"[a-zA-Z0-9_\\\\-]*\"\n    },\n    \"CurrentRevisionId\": {\n      \"description\": \"The current revision id.\",\n      \"type\": \"string\"\n    },\n    \"RenderingEngine\" : {\n      \"description\": \"The rendering engine for the simulation application.\",\n      \"$ref\": \"#/definitions/RenderingEngine\"\n    },\n    \"RobotSoftwareSuite\" : {\n      \"description\": \"The robot software suite used by the simulation application.\",\n      \"$ref\": \"#/definitions/RobotSoftwareSuite\"\n    },\n    \"SimulationSoftwareSuite\" : {\n      \"description\": \"The simulation software suite used by the simulation application.\",\n      \"$ref\": \"#/definitions/SimulationSoftwareSuite\"\n    },\n    \"Sources\": {\n      \"description\": \"The sources of the simulation application.\",\n      \"type\": \"array\",\n      \"insertionOrder\": false,\n      \"items\": {\n        \"$ref\": \"#/definitions/SourceConfig\"\n      }\n    },\n    \"Environment\": {\n      \"description\": \"The URI of the Docker image for the robot application.\",\n      \"type\": \"string\"\n    },\n    \"Tags\": {\n      \"$ref\": \"#/definitions/Tags\"\n    }\n  },\n  \"additionalProperties\": false,\n  \"required\": [\n    \"RobotSoftwareSuite\",\n    \"SimulationSoftwareSuite\"\n  ],\n  \"readOnlyProperties\": [\n    \"/properties/Arn\"\n  ],\n  \"writeOnlyProperties\": [\n    \"/properties/RenderingEngine\",\n    \"/properties/RobotSoftwareSuite/Version\",\n    \"/properties/Sources\",\n    \"/properties/SimulationSoftwareSuite/Version\"\n  ],\n  \"createOnlyProperties\": [\n    \"/properties/Name\"\n  ],\n  \"primaryIdentifier\": [\n    \"/properties/Arn\"\n  ],\n  \"handlers\": {\n    \"create\": {\n      \"permissions\": [\n        \"robomaker:CreateSimulationApplication\"\n      ]\n    },\n    \"read\": {\n      \"permissions\": [\n        \"robomaker:DescribeSimulationApplication\"\n      ]\n    },\n    \"update\": {\n      \"permissions\": [\n        \"robomaker:TagResource\",\n        \"robomaker:UntagResource\",\n        \"robomaker:UpdateSimulationApplication\"\n      ]\n    },\n    \"delete\": {\n      \"permissions\": [\n        \"robomaker:DeleteSimulationApplication\"\n      ]\n    },\n    \"list\": {\n      \"permissions\": [\n        \"robomaker:ListSimulationApplications\"\n      ]\n    }\n  }\n}\n",
    "ProvisioningType": "FULLY_MUTABLE",
    "DeprecatedStatus": "LIVE",
    "Visibility": "PUBLIC",
    "SourceUrl": "https://github.com/aws-cloudformation/aws-cloudformation-rpdk.git",
    "TimeCreated": "2021-08-05T19:14:00.668000+00:00"
}
