{
    "Arn": "arn:aws:cloudformation:us-east-1::type/resource/AWS-CodeStar-GitHubRepository",
    "Type": "RESOURCE",
    "TypeName": "AWS::CodeStar::GitHubRepository",
    "IsDefaultVersion": true,
    "Schema": "{\n  \"typeName\": \"AWS::CodeStar::GitHubRepository\",\n  \"description\": \"Resource Type definition for AWS::CodeStar::GitHubRepository\",\n  \"additionalProperties\": false,\n  \"properties\": {\n    \"EnableIssues\": {\n      \"type\": \"boolean\"\n    },\n    \"ConnectionArn\": {\n      \"type\": \"string\"\n    },\n    \"RepositoryName\": {\n      \"type\": \"string\"\n    },\n    \"RepositoryAccessToken\": {\n      \"type\": \"string\"\n    },\n    \"Id\": {\n      \"type\": \"string\"\n    },\n    \"RepositoryOwner\": {\n      \"type\": \"string\"\n    },\n    \"IsPrivate\": {\n      \"type\": \"boolean\"\n    },\n    \"Code\": {\n      \"$ref\": \"#/definitions/Code\"\n    },\n    \"RepositoryDescription\": {\n      \"type\": \"string\"\n    }\n  },\n  \"definitions\": {\n    \"S3\": {\n      \"type\": \"object\",\n      \"additionalProperties\": false,\n      \"properties\": {\n        \"ObjectVersion\": {\n          \"type\": \"string\"\n        },\n        \"Bucket\": {\n          \"type\": \"string\"\n        },\n        \"Key\": {\n          \"type\": \"string\"\n        }\n      },\n      \"required\": [\n        \"Bucket\",\n        \"Key\"\n      ]\n    },\n    \"Code\": {\n      \"type\": \"object\",\n      \"additionalProperties\": false,\n      \"properties\": {\n        \"S3\": {\n          \"$ref\": \"#/definitions/S3\"\n        }\n      },\n      \"required\": [\n        \"S3\"\n      ]\n    }\n  },\n  \"required\": [\n    \"RepositoryName\",\n    \"RepositoryOwner\"\n  ],\n  \"primaryIdentifier\": [\n    \"/properties/Id\"\n  ],\n  \"readOnlyProperties\": [\n    \"/properties/Id\"\n  ]\n}",
    "ProvisioningType": "NON_PROVISIONABLE",
    "DeprecatedStatus": "LIVE",
    "Visibility": "PUBLIC",
    "TimeCreated": "2019-11-15T17:25:48.406000+00:00"
}
