{
    "Arn": "arn:aws:cloudformation:us-east-1::type/resource/AWS-AmplifyUIBuilder-Component",
    "Type": "RESOURCE",
    "TypeName": "AWS::AmplifyUIBuilder::Component",
    "IsDefaultVersion": true,
    "Description": "Definition of AWS::AmplifyUIBuilder::Component Resource Type",
    "Schema": "{\n  \"typeName\": \"AWS::AmplifyUIBuilder::Component\",\n  \"description\": \"Definition of AWS::AmplifyUIBuilder::Component Resource Type\",\n  \"sourceUrl\": \"https://github.com/aws-cloudformation/aws-cloudformation-resource-providers-amplifyuibuilder\",\n  \"definitions\": {\n    \"ActionParameters\": {\n      \"type\": \"object\",\n      \"properties\": {\n        \"Type\": {\n          \"$ref\": \"#/definitions/ComponentProperty\"\n        },\n        \"Url\": {\n          \"$ref\": \"#/definitions/ComponentProperty\"\n        },\n        \"Anchor\": {\n          \"$ref\": \"#/definitions/ComponentProperty\"\n        },\n        \"Target\": {\n          \"$ref\": \"#/definitions/ComponentProperty\"\n        },\n        \"Global\": {\n          \"$ref\": \"#/definitions/ComponentProperty\"\n        },\n        \"Model\": {\n          \"type\": \"string\"\n        },\n        \"Id\": {\n          \"$ref\": \"#/definitions/ComponentProperty\"\n        },\n        \"Fields\": {\n          \"$ref\": \"#/definitions/ComponentProperties\"\n        },\n        \"State\": {\n          \"$ref\": \"#/definitions/MutationActionSetStateParameter\"\n        }\n      },\n      \"additionalProperties\": false\n    },\n    \"ComponentBindingProperties\": {\n      \"type\": \"object\",\n      \"patternProperties\": {\n        \".+\": {\n          \"$ref\": \"#/definitions/ComponentBindingPropertiesValue\"\n        }\n      },\n      \"additionalProperties\": false\n    },\n    \"ComponentBindingPropertiesValue\": {\n      \"type\": \"object\",\n      \"properties\": {\n        \"Type\": {\n          \"type\": \"string\"\n        },\n        \"BindingProperties\": {\n          \"$ref\": \"#/definitions/ComponentBindingPropertiesValueProperties\"\n        },\n        \"DefaultValue\": {\n          \"type\": \"string\"\n        }\n      },\n      \"additionalProperties\": false\n    },\n    \"ComponentBindingPropertiesValueProperties\": {\n      \"type\": \"object\",\n      \"properties\": {\n        \"Model\": {\n          \"type\": \"string\"\n        },\n        \"Field\": {\n          \"type\": \"string\"\n        },\n        \"Predicates\": {\n          \"type\": \"array\",\n          \"items\": {\n            \"$ref\": \"#/definitions/Predicate\"\n          }\n        },\n        \"UserAttribute\": {\n          \"type\": \"string\"\n        },\n        \"Bucket\": {\n          \"type\": \"string\"\n        },\n        \"Key\": {\n          \"type\": \"string\"\n        },\n        \"DefaultValue\": {\n          \"type\": \"string\"\n        }\n      },\n      \"additionalProperties\": false\n    },\n    \"ComponentChild\": {\n      \"type\": \"object\",\n      \"properties\": {\n        \"ComponentType\": {\n          \"type\": \"string\"\n        },\n        \"Name\": {\n          \"type\": \"string\"\n        },\n        \"Properties\": {\n          \"$ref\": \"#/definitions/ComponentProperties\"\n        },\n        \"Children\": {\n          \"type\": \"array\",\n          \"items\": {\n            \"$ref\": \"#/definitions/ComponentChild\"\n          }\n        },\n        \"Events\": {\n          \"$ref\": \"#/definitions/ComponentEvents\"\n        }\n      },\n      \"required\": [\n        \"ComponentType\",\n        \"Name\",\n        \"Properties\"\n      ],\n      \"additionalProperties\": false\n    },\n    \"ComponentCollectionProperties\": {\n      \"type\": \"object\",\n      \"patternProperties\": {\n        \".+\": {\n          \"$ref\": \"#/definitions/ComponentDataConfiguration\"\n        }\n      },\n      \"additionalProperties\": false\n    },\n    \"ComponentConditionProperty\": {\n      \"type\": \"object\",\n      \"properties\": {\n        \"Property\": {\n          \"type\": \"string\"\n        },\n        \"Field\": {\n          \"type\": \"string\"\n        },\n        \"Operator\": {\n          \"type\": \"string\"\n        },\n        \"Operand\": {\n          \"type\": \"string\"\n        },\n        \"Then\": {\n          \"$ref\": \"#/definitions/ComponentProperty\"\n        },\n        \"Else\": {\n          \"$ref\": \"#/definitions/ComponentProperty\"\n        },\n        \"OperandType\": {\n          \"type\": \"string\"\n        }\n      },\n      \"additionalProperties\": false\n    },\n    \"ComponentDataConfiguration\": {\n      \"type\": \"object\",\n      \"properties\": {\n        \"Model\": {\n          \"type\": \"string\"\n        },\n        \"Sort\": {\n          \"type\": \"array\",\n          \"items\": {\n            \"$ref\": \"#/definitions/SortProperty\"\n          }\n        },\n        \"Predicate\": {\n          \"$ref\": \"#/definitions/Predicate\"\n        },\n        \"Identifiers\": {\n          \"type\": \"array\",\n          \"items\": {\n            \"type\": \"string\"\n          }\n        }\n      },\n      \"required\": [\n        \"Model\"\n      ],\n      \"additionalProperties\": false\n    },\n    \"ComponentEvent\": {\n      \"type\": \"object\",\n      \"properties\": {\n        \"Action\": {\n          \"type\": \"string\"\n        },\n        \"Parameters\": {\n          \"$ref\": \"#/definitions/ActionParameters\"\n        }\n      },\n      \"additionalProperties\": false\n    },\n    \"ComponentEvents\": {\n      \"type\": \"object\",\n      \"patternProperties\": {\n        \".+\": {\n          \"$ref\": \"#/definitions/ComponentEvent\"\n        }\n      },\n      \"additionalProperties\": false\n    },\n    \"ComponentOverrides\": {\n      \"type\": \"object\",\n      \"patternProperties\": {\n        \".+\": {\n          \"$ref\": \"#/definitions/ComponentOverridesValue\"\n        }\n      },\n      \"additionalProperties\": false\n    },\n    \"ComponentOverridesValue\": {\n      \"type\": \"object\",\n      \"patternProperties\": {\n        \".+\": {\n          \"type\": \"string\"\n        }\n      },\n      \"additionalProperties\": false\n    },\n    \"ComponentProperties\": {\n      \"type\": \"object\",\n      \"patternProperties\": {\n        \".+\": {\n          \"$ref\": \"#/definitions/ComponentProperty\"\n        }\n      },\n      \"additionalProperties\": false\n    },\n    \"ComponentProperty\": {\n      \"type\": \"object\",\n      \"properties\": {\n        \"Value\": {\n          \"type\": \"string\"\n        },\n        \"BindingProperties\": {\n          \"$ref\": \"#/definitions/ComponentPropertyBindingProperties\"\n        },\n        \"CollectionBindingProperties\": {\n          \"$ref\": \"#/definitions/ComponentPropertyBindingProperties\"\n        },\n        \"DefaultValue\": {\n          \"type\": \"string\"\n        },\n        \"Model\": {\n          \"type\": \"string\"\n        },\n        \"Bindings\": {\n          \"$ref\": \"#/definitions/FormBindings\"\n        },\n        \"Event\": {\n          \"type\": \"string\"\n        },\n        \"UserAttribute\": {\n          \"type\": \"string\"\n        },\n        \"Concat\": {\n          \"type\": \"array\",\n          \"items\": {\n            \"$ref\": \"#/definitions/ComponentProperty\"\n          }\n        },\n        \"Condition\": {\n          \"$ref\": \"#/definitions/ComponentConditionProperty\"\n        },\n        \"Configured\": {\n          \"type\": \"boolean\"\n        },\n        \"Type\": {\n          \"type\": \"string\"\n        },\n        \"ImportedValue\": {\n          \"type\": \"string\"\n        },\n        \"ComponentName\": {\n          \"type\": \"string\"\n        },\n        \"Property\": {\n          \"type\": \"string\"\n        }\n      },\n      \"additionalProperties\": false\n    },\n    \"ComponentPropertyBindingProperties\": {\n      \"type\": \"object\",\n      \"properties\": {\n        \"Property\": {\n          \"type\": \"string\"\n        },\n        \"Field\": {\n          \"type\": \"string\"\n        }\n      },\n      \"required\": [\n        \"Property\"\n      ],\n      \"additionalProperties\": false\n    },\n    \"ComponentVariant\": {\n      \"type\": \"object\",\n      \"properties\": {\n        \"VariantValues\": {\n          \"$ref\": \"#/definitions/ComponentVariantValues\"\n        },\n        \"Overrides\": {\n          \"$ref\": \"#/definitions/ComponentOverrides\"\n        }\n      },\n      \"additionalProperties\": false\n    },\n    \"ComponentVariantValues\": {\n      \"type\": \"object\",\n      \"patternProperties\": {\n        \".+\": {\n          \"type\": \"string\"\n        }\n      },\n      \"additionalProperties\": false\n    },\n    \"FormBindingElement\": {\n      \"type\": \"object\",\n      \"properties\": {\n        \"Element\": {\n          \"type\": \"string\"\n        },\n        \"Property\": {\n          \"type\": \"string\"\n        }\n      },\n      \"required\": [\n        \"Element\",\n        \"Property\"\n      ],\n      \"additionalProperties\": false\n    },\n    \"FormBindings\": {\n      \"type\": \"object\",\n      \"patternProperties\": {\n        \".+\": {\n          \"$ref\": \"#/definitions/FormBindingElement\"\n        }\n      },\n      \"additionalProperties\": false\n    },\n    \"MutationActionSetStateParameter\": {\n      \"type\": \"object\",\n      \"properties\": {\n        \"ComponentName\": {\n          \"type\": \"string\"\n        },\n        \"Property\": {\n          \"type\": \"string\"\n        },\n        \"Set\": {\n          \"$ref\": \"#/definitions/ComponentProperty\"\n        }\n      },\n      \"required\": [\n        \"ComponentName\",\n        \"Property\",\n        \"Set\"\n      ],\n      \"additionalProperties\": false\n    },\n    \"Predicate\": {\n      \"type\": \"object\",\n      \"properties\": {\n        \"Or\": {\n          \"type\": \"array\",\n          \"items\": {\n            \"$ref\": \"#/definitions/Predicate\"\n          }\n        },\n        \"And\": {\n          \"type\": \"array\",\n          \"items\": {\n            \"$ref\": \"#/definitions/Predicate\"\n          }\n        },\n        \"Field\": {\n          \"type\": \"string\"\n        },\n        \"Operator\": {\n          \"type\": \"string\"\n        },\n        \"Operand\": {\n          \"type\": \"string\"\n        }\n      },\n      \"additionalProperties\": false\n    },\n    \"SortDirection\": {\n      \"type\": \"string\",\n      \"enum\": [\n        \"ASC\",\n        \"DESC\"\n      ]\n    },\n    \"SortProperty\": {\n      \"type\": \"object\",\n      \"properties\": {\n        \"Field\": {\n          \"type\": \"string\"\n        },\n        \"Direction\": {\n          \"$ref\": \"#/definitions/SortDirection\"\n        }\n      },\n      \"required\": [\n        \"Direction\",\n        \"Field\"\n      ],\n      \"additionalProperties\": false\n    },\n    \"Tags\": {\n      \"type\": \"object\",\n      \"patternProperties\": {\n        \"^(?!aws:)[a-zA-Z+-=._:/]+$\": {\n          \"type\": \"string\",\n          \"maxLength\": 256,\n          \"minLength\": 1\n        }\n      },\n      \"additionalProperties\": false\n    }\n  },\n  \"properties\": {\n    \"AppId\": {\n      \"type\": \"string\"\n    },\n    \"BindingProperties\": {\n      \"$ref\": \"#/definitions/ComponentBindingProperties\"\n    },\n    \"Children\": {\n      \"type\": \"array\",\n      \"items\": {\n        \"$ref\": \"#/definitions/ComponentChild\"\n      }\n    },\n    \"CollectionProperties\": {\n      \"$ref\": \"#/definitions/ComponentCollectionProperties\"\n    },\n    \"ComponentType\": {\n      \"type\": \"string\",\n      \"maxLength\": 255,\n      \"minLength\": 1\n    },\n    \"EnvironmentName\": {\n      \"type\": \"string\"\n    },\n    \"Events\": {\n      \"$ref\": \"#/definitions/ComponentEvents\"\n    },\n    \"Id\": {\n      \"type\": \"string\"\n    },\n    \"Name\": {\n      \"type\": \"string\",\n      \"maxLength\": 255,\n      \"minLength\": 1\n    },\n    \"Overrides\": {\n      \"$ref\": \"#/definitions/ComponentOverrides\"\n    },\n    \"Properties\": {\n      \"$ref\": \"#/definitions/ComponentProperties\"\n    },\n    \"SchemaVersion\": {\n      \"type\": \"string\"\n    },\n    \"SourceId\": {\n      \"type\": \"string\"\n    },\n    \"Tags\": {\n      \"$ref\": \"#/definitions/Tags\"\n    },\n    \"Variants\": {\n      \"type\": \"array\",\n      \"items\": {\n        \"$ref\": \"#/definitions/ComponentVariant\"\n      }\n    }\n  },\n  \"required\": [\n    \"BindingProperties\",\n    \"ComponentType\",\n    \"Name\",\n    \"Overrides\",\n    \"Properties\",\n    \"Variants\"\n  ],\n  \"readOnlyProperties\": [\n    \"/properties/Id\"\n  ],\n  \"createOnlyProperties\": [\n    \"/properties/Tags\"\n  ],\n  \"primaryIdentifier\": [\n    \"/properties/AppId\",\n    \"/properties/EnvironmentName\",\n    \"/properties/Id\"\n  ],\n  \"handlers\": {\n    \"create\": {\n      \"permissions\": [\n        \"amplify:GetApp\",\n        \"amplifyuibuilder:GetComponent\",\n        \"amplifyuibuilder:CreateComponent\",\n        \"amplifyuibuilder:TagResource\"\n      ]\n    },\n    \"read\": {\n      \"permissions\": [\n        \"amplify:GetApp\",\n        \"amplifyuibuilder:GetComponent\"\n      ]\n    },\n    \"update\": {\n      \"permissions\": [\n        \"amplify:GetApp\",\n        \"amplifyuibuilder:GetComponent\",\n        \"amplifyuibuilder:UpdateComponent\",\n        \"amplifyuibuilder:TagResource\"\n      ]\n    },\n    \"delete\": {\n      \"permissions\": [\n        \"amplify:GetApp\",\n        \"amplifyuibuilder:GetComponent\",\n        \"amplifyuibuilder:DeleteComponent\",\n        \"amplifyuibuilder:UntagResource\"\n      ]\n    },\n    \"list\": {\n      \"permissions\": [\n        \"amplify:GetApp\",\n        \"amplifyuibuilder:GetComponent\",\n        \"amplifyuibuilder:ListComponents\"\n      ],\n      \"handlerSchema\": {\n        \"properties\": {\n          \"AppId\": {\n            \"$ref\": \"resource-schema.json#/properties/AppId\"\n          },\n          \"EnvironmentName\": {\n            \"$ref\": \"resource-schema.json#/properties/EnvironmentName\"\n          }\n        },\n        \"required\": [\n          \"AppId\",\n          \"EnvironmentName\"\n        ]\n      }\n    }\n  },\n  \"tagging\": {\n    \"taggable\": true,\n    \"tagOnCreate\": true,\n    \"tagUpdatable\": false,\n    \"cloudFormationSystemTags\": false,\n    \"tagProperty\": \"#/properties/Tags\"\n  },\n  \"additionalProperties\": false\n}",
    "ProvisioningType": "FULLY_MUTABLE",
    "DeprecatedStatus": "LIVE",
    "Visibility": "PUBLIC",
    "SourceUrl": "https://github.com/aws-cloudformation/aws-cloudformation-resource-providers-amplifyuibuilder",
    "TimeCreated": "2021-11-23T20:45:27.372000+00:00"
}
