{
    "Arn": "arn:aws:cloudformation:us-east-1::type/resource/AWS-ServiceCatalogAppRegistry-ResourceAssociation",
    "Type": "RESOURCE",
    "TypeName": "AWS::ServiceCatalogAppRegistry::ResourceAssociation",
    "IsDefaultVersion": true,
    "Description": "Resource Schema for AWS::ServiceCatalogAppRegistry::ResourceAssociation",
    "Schema": "{\n  \"typeName\": \"AWS::ServiceCatalogAppRegistry::ResourceAssociation\",\n  \"description\": \"Resource Schema for AWS::ServiceCatalogAppRegistry::ResourceAssociation\",\n  \"sourceUrl\": \"https://github.com/aws-cloudformation/aws-cloudformation-resource-providers-servicecatalog-appregistry.git\",\n  \"documentationUrl\": \"https://docs.aws.amazon.com/AWSCloudFormation/latest/UserGuide/aws-resource-servicecatalog-appregistry-resourceassociation.html\",\n  \"properties\": {\n    \"Application\": {\n      \"type\": \"string\",\n      \"description\": \"The name or the Id of the Application.\",\n      \"minLength\": 1,\n      \"maxLength\": 256,\n      \"pattern\": \"\\\\w+|[a-z0-9]{12}\"\n    },\n    \"Resource\": {\n      \"type\": \"string\",\n      \"description\": \"The name or the Id of the Resource.\",\n      \"pattern\": \"\\\\w+|arn:aws[-a-z]*:cloudformation:[a-z]{2}(-gov)?-[a-z]+-\\\\d:\\\\d{12}:stack/[a-zA-Z][-A-Za-z0-9]{0,127}/[0-9a-f]{8}(-[0-9a-f]{4}){3}-[0-9a-f]{12}\"\n    },\n    \"ResourceType\": {\n      \"type\": \"string\",\n      \"description\": \"The type of the CFN Resource for now it's enum CFN_STACK.\",\n      \"enum\": [\n        \"CFN_STACK\"\n      ]\n    },\n    \"ApplicationArn\": {\n      \"type\": \"string\",\n      \"pattern\": \"arn:aws[-a-z]*:servicecatalog:[a-z]{2}(-gov)?-[a-z]+-\\\\d:\\\\d{12}:/applications/[a-z0-9]+\"\n    },\n    \"ResourceArn\": {\n      \"type\": \"string\",\n      \"pattern\": \"arn:aws[-a-z]*:cloudformation:[a-z]{2}(-gov)?-[a-z]+-\\\\d:\\\\d{12}:stack/[a-zA-Z][-A-Za-z0-9]{0,127}/[0-9a-f]{8}(-[0-9a-f]{4}){3}-[0-9a-f]{12}\"\n    },\n    \"Id\": {\n      \"type\": \"string\"\n    }\n  },\n  \"additionalProperties\": false,\n  \"required\": [\n    \"Application\",\n    \"Resource\",\n    \"ResourceType\"\n  ],\n  \"readOnlyProperties\": [\n    \"/properties/ApplicationArn\",\n    \"/properties/ResourceArn\",\n    \"/properties/Id\"\n  ],\n  \"createOnlyProperties\": [\n    \"/properties/Application\",\n    \"/properties/Resource\",\n    \"/properties/ResourceType\"\n  ],\n  \"primaryIdentifier\": [\n    \"/properties/Id\"\n  ],\n  \"taggable\": false,\n  \"handlers\": {\n    \"create\": {\n      \"permissions\": [\n        \"servicecatalog:AssociateResource\",\n        \"cloudformation:DescribeStacks\"\n      ]\n    },\n    \"read\": {\n      \"permissions\": [\n        \"servicecatalog:ListAssociatedResources\"\n      ]\n    },\n    \"delete\": {\n      \"permissions\": [\n        \"servicecatalog:DisassociateResource\"\n      ]\n    }\n  }\n}\n",
    "ProvisioningType": "IMMUTABLE",
    "DeprecatedStatus": "LIVE",
    "Visibility": "PUBLIC",
    "SourceUrl": "https://github.com/aws-cloudformation/aws-cloudformation-resource-providers-servicecatalog-appregistry.git",
    "DocumentationUrl": "https://docs.aws.amazon.com/AWSCloudFormation/latest/UserGuide/aws-resource-servicecatalog-appregistry-resourceassociation.html",
    "TimeCreated": "2020-11-21T21:17:27.595000+00:00"
}
