{
    "Arn": "arn:aws:cloudformation:us-east-1::type/resource/AWS-SSM-Association",
    "Type": "RESOURCE",
    "TypeName": "AWS::SSM::Association",
    "IsDefaultVersion": true,
    "Description": "The AWS::SSM::Association resource associates an SSM document in AWS Systems Manager with EC2 instances that contain a configuration agent to process the document.",
    "Schema": "{\n    \"typeName\": \"AWS::SSM::Association\",\n    \"description\": \"The AWS::SSM::Association resource associates an SSM document in AWS Systems Manager with EC2 instances that contain a configuration agent to process the document.\",\n    \"sourceUrl\": \"https://github.com/aws-cloudformation/aws-cloudformation-resource-providers-ssm\",\n    \"definitions\": {\n        \"Target\": {\n            \"type\": \"object\",\n            \"properties\": {\n                \"Key\": {\n                    \"type\": \"string\",\n                    \"pattern\": \"^[\\\\p{L}\\\\p{Z}\\\\p{N}_.:/=+\\\\-@]{1,128}$|resource-groups:Name\"\n                },\n                \"Values\": {\n                    \"type\": \"array\",\n                    \"items\": {\n                        \"type\": \"string\"\n                    },\n                    \"minItems\": 0,\n                    \"maxItems\": 50\n                }\n            },\n            \"additionalProperties\": false,\n            \"required\": [\n                \"Key\",\n                \"Values\"\n            ]\n        },\n        \"ParameterValues\": {\n            \"type\": \"array\",\n            \"items\": {\n                \"type\": \"string\"\n            }\n        },\n        \"S3Region\": {\n            \"type\": \"string\",\n            \"minLength\": 3,\n            \"maxLength\": 20\n        },\n        \"S3BucketName\": {\n            \"type\": \"string\",\n            \"minLength\": 3,\n            \"maxLength\": 63\n        },\n        \"S3KeyPrefix\": {\n            \"type\": \"string\",\n            \"maxLength\": 1024\n        },\n        \"S3OutputLocation\": {\n            \"type\": \"object\",\n            \"properties\": {\n                \"OutputS3Region\": {\n                    \"$ref\": \"#/definitions/S3Region\"\n                },\n                \"OutputS3BucketName\": {\n                    \"$ref\": \"#/definitions/S3BucketName\"\n                },\n                \"OutputS3KeyPrefix\": {\n                    \"$ref\": \"#/definitions/S3KeyPrefix\"\n                }\n            },\n            \"additionalProperties\": false\n        },\n        \"InstanceAssociationOutputLocation\": {\n            \"type\": \"object\",\n            \"properties\": {\n                \"S3Location\": {\n                    \"$ref\": \"#/definitions/S3OutputLocation\"\n                }\n            },\n            \"additionalProperties\": false\n        }\n    },\n    \"properties\": {\n        \"AssociationId\": {\n            \"description\": \"Unique identifier of the association.\",\n            \"type\": \"string\",\n            \"pattern\": \"[0-9a-fA-F]{8}-[0-9a-fA-F]{4}-[0-9a-fA-F]{4}-[0-9a-fA-F]{4}-[0-9a-fA-F]{12}\",\n            \"examples\": [\n                \"88df7b09-95e8-48c4-a3cb-08c2c20d5110\",\n                \"203dd0ec-0055-4bf0-a872-707f72ef06aa\"\n            ]\n        },\n        \"AssociationName\": {\n            \"description\": \"The name of the association.\",\n            \"type\": \"string\",\n            \"pattern\": \"^[a-zA-Z0-9_\\\\-.]{3,128}$\"\n        },\n        \"DocumentVersion\": {\n            \"description\": \"The version of the SSM document to associate with the target.\",\n            \"type\": \"string\",\n            \"pattern\": \"([$]LATEST|[$]DEFAULT|^[1-9][0-9]*$)\"\n        },\n        \"InstanceId\": {\n            \"description\": \"The ID of the instance that the SSM document is associated with.\",\n            \"type\": \"string\",\n            \"pattern\": \"(^i-(\\\\w{8}|\\\\w{17})$)|(^mi-\\\\w{17}$)\",\n            \"examples\": [\n                \"i-0e60836d21cf313c4\",\n                \"mi-0532c22e49636ee13\"\n            ]\n        },\n        \"Name\": {\n            \"description\": \"The name of the SSM document.\",\n            \"type\": \"string\",\n            \"pattern\": \"^[a-zA-Z0-9_\\\\-.:/]{3,200}$\",\n            \"examples\": [\n                \"AWS-GatherSoftwareInventory\",\n                \"MyCustomSSMDocument\"\n            ]\n        },\n        \"Parameters\": {\n            \"description\": \"Parameter values that the SSM document uses at runtime.\",\n            \"type\": \"object\",\n            \"patternProperties\": {\n                \".*{1,255}\": {\n                    \"$ref\": \"#/definitions/ParameterValues\"\n                }\n            },\n            \"additionalProperties\": false\n        },\n        \"ScheduleExpression\": {\n            \"description\": \"A Cron or Rate expression that specifies when the association is applied to the target.\",\n            \"type\": \"string\",\n            \"minLength\": 1,\n            \"maxLength\": 256,\n            \"examples\": [\n                \"cron(0 0 */1 * * ? *)\",\n                \"cron(0 16 ? * TUE *)\",\n                \"rate(30 minutes)\",\n                \"rate(7 days)\"\n            ]\n        },\n        \"Targets\": {\n            \"description\": \"The targets that the SSM document sends commands to.\",\n            \"type\": \"array\",\n            \"items\": {\n                \"$ref\": \"#/definitions/Target\"\n            },\n            \"minItems\": 0,\n            \"maxItems\": 5\n        },\n        \"OutputLocation\": {\n            \"$ref\": \"#/definitions/InstanceAssociationOutputLocation\"\n        },\n        \"AutomationTargetParameterName\": {\n            \"type\": \"string\",\n            \"minLength\": 1,\n            \"maxLength\": 50\n        },\n        \"MaxErrors\": {\n            \"type\": \"string\",\n            \"pattern\": \"^([1-9][0-9]{0,6}|[0]|[1-9][0-9]%|[0-9]%|100%)$\",\n            \"examples\": [\n                \"1%\",\n                \"10%\",\n                \"50%\",\n                \"1\"\n            ]\n        },\n        \"MaxConcurrency\": {\n            \"type\": \"string\",\n            \"pattern\": \"^([1-9][0-9]{0,6}|[1-9][0-9]%|[1-9]%|100%)$\",\n            \"examples\": [\n                \"1%\",\n                \"10%\",\n                \"50%\",\n                \"1\"\n            ]\n        },\n        \"ComplianceSeverity\": {\n            \"type\": \"string\",\n            \"enum\": [\n                \"CRITICAL\",\n                \"HIGH\",\n                \"MEDIUM\",\n                \"LOW\",\n                \"UNSPECIFIED\"\n            ]\n        },\n        \"SyncCompliance\": {\n            \"type\": \"string\",\n            \"enum\": [\n                \"AUTO\",\n                \"MANUAL\"\n            ]\n        },\n        \"WaitForSuccessTimeoutSeconds\": {\n            \"type\": \"integer\",\n            \"minimum\": 15,\n            \"maximum\": 172800\n        },\n        \"ApplyOnlyAtCronInterval\": {\n            \"type\": \"boolean\"\n        },\n        \"CalendarNames\": {\n            \"type\": \"array\",\n            \"items\": {\n                \"type\": \"string\"\n            },\n            \"examples\": [\n                [\n                    \"calendar1\",\n                    \"calendar2\"\n                ],\n                [\n                    \"calendar3\"\n                ]\n            ]\n        },\n        \"ScheduleOffset\": {\n            \"type\": \"integer\",\n            \"minimum\": 1,\n            \"maximum\": 6\n        }\n    },\n    \"required\": [\n        \"Name\"\n    ],\n    \"readOnlyProperties\": [\n        \"/properties/AssociationId\"\n    ],\n    \"primaryIdentifier\": [\n        \"/properties/AssociationId\"\n    ],\n    \"tagging\": {\n        \"taggable\": false\n    },\n    \"handlers\": {\n        \"create\": {\n            \"permissions\": [\n                \"ec2:DescribeInstanceStatus\",\n                \"iam:PassRole\",\n                \"ssm:CreateAssociation\",\n                \"ssm:DescribeAssociation\"\n            ]\n        },\n        \"delete\": {\n            \"permissions\": [\n                \"ssm:DeleteAssociation\"\n            ]\n        },\n        \"update\": {\n            \"permissions\": [\n                \"iam:PassRole\",\n                \"ssm:UpdateAssociation\"\n            ]\n        },\n        \"read\": {\n            \"permissions\": [\n                \"ssm:DescribeAssociation\",\n                \"resource-groups:GetGroupQuery\",\n                \"resource-groups:ListGroups\",\n                \"resource-groups:ListGroupResources\"\n            ]\n        },\n        \"list\": {\n            \"permissions\": [\n                \"ssm:ListAssociations\"\n            ]\n        }\n    },\n    \"additionalProperties\": false\n}\n",
    "ProvisioningType": "FULLY_MUTABLE",
    "DeprecatedStatus": "LIVE",
    "Visibility": "PUBLIC",
    "SourceUrl": "https://github.com/aws-cloudformation/aws-cloudformation-resource-providers-ssm",
    "TimeCreated": "2020-03-10T03:00:34.130000+00:00"
}
